Metadata-Version: 2.4
Name: alltheplots
Version: 0.1.0
Summary: Intuitive automatic plotting for arrays of any dimensionality
Home-page: https://github.com/gomezzz/alltheplots
Author: Pablo Gómez
Author-email: contact@pablo-gomez.net
Project-URL: Source, https://github.com/gomezzz/alltheplots/
Project-URL: Bug Reports, https://github.com/gomezzz/alltheplots/issues
Classifier: Development Status :: 3 - Alpha
Classifier: Intended Audience :: Developers
Classifier: Intended Audience :: Science/Research
Classifier: Topic :: Scientific/Engineering :: Visualization
Classifier: License :: OSI Approved :: GNU General Public License v3 (GPLv3)
Classifier: Programming Language :: Python :: 3.9
Classifier: Programming Language :: Python :: 3.10
Classifier: Programming Language :: Python :: 3.11
Requires-Python: >=3.9
License-File: LICENSE
Requires-Dist: loguru>=0.6.0
Requires-Dist: matplotlib>=3.6.0
Requires-Dist: numpy>=1.23.5
Requires-Dist: scipy>=1.9.0
Requires-Dist: seaborn>=0.12.0
Requires-Dist: scikit-learn>=1.0.0
Requires-Dist: umap-learn>=0.5.0
Dynamic: author
Dynamic: author-email
Dynamic: classifier
Dynamic: description
Dynamic: description-content-type
Dynamic: home-page
Dynamic: license-file
Dynamic: project-url
Dynamic: requires-dist
Dynamic: requires-python
Dynamic: summary
